{"_type":"export","__export_format":4,"__export_date":"2025-02-05T23:39:19.944Z","__export_source":"insomnia.desktop.app:v10.3.0","resources":[{"_id":"req_a120fbf2ca1143e0912a6a2aaffd79f9","parentId":"wrk_fe311232e0ad4a948aa3f7055e7308cb","modified":1738798723218,"created":1738792744988,"url":"https://api.dev.iu-quiz.de/question","name":"GET question","description":"","method":"GET","body":{},"parameters":[],"headers":[{"name":"User-Agent","value":"insomnia/10.3.0"}],"authentication":{},"metaSortKey":-1738792744988,"isPrivate":false,"pathParameters":[],"settingStoreCookies":true,"settingSendCookies":true,"settingDisableRenderRequestBody":false,"settingEncodeUrl":true,"settingRebuildPath":true,"settingFollowRedirects":"global","_type":"request"},{"_id":"wrk_fe311232e0ad4a948aa3f7055e7308cb","parentId":null,"modified":1738792693907,"created":1738792693907,"name":"iu-quiz-app","description":"","scope":"collection","_type":"workspace"},{"_id":"req_8827e7d0b86547efa82ba4a78e9c04fb","parentId":"wrk_fe311232e0ad4a948aa3f7055e7308cb","modified":1738798524171,"created":1738792698761,"url":"https://api.dev.iu-quiz.de/question","name":"Create new question","description":"","method":"POST","body":{"mimeType":"application/json","text":"{\n\t\"course\": \"TestKurs\",\n\t\"text\": \"Schafft Philipp es die Testfrage zu deployen?\",\n\t\"creator_user_id\": \"23479lsdfkjPhilipp\",\n\t\"answers\": [\n\t\t{\n\t\t\t\"isTrue\": true,\n\t\t\t\"text\": \"Philipp wird schaffen!\",\n\t\t\t\"explanation\": \"Philipp hat es einfach drauf, deswegen hat er es geschafft!\"\n\t\t},\n\t\t{\n\t\t\t\"isTrue\": false,\n\t\t\t\"text\": \"Philipp verkackt es!\",\n\t\t\t\"explanation\": \"Philipp ist dumm, deswegen hat er es verkackt!\"\n\t\t},\n\t\t{\n\t\t\t\"isTrue\": false,\n\t\t\t\"text\": \"Philipp schafft es nicht!\",\n\t\t\t\"explanation\": \"Es fehlt nur noch ein bisschen, aber bald hat er es!\"\n\t\t},\n\t\t{\n\t\t\t\"isTrue\": false,\n\t\t\t\"text\": \"Es ist zu spät in der Nacht, deswegen kann Philipp sich nicht mehr konzentrieren!\",\n\t\t\t\"explanation\": \"Philipp sollte ins Bett gehen und ausgeschlafen weiterarbeiten!\"\n\t\t}\n\t]\n}"},"parameters":[],"headers":[{"name":"Content-Type","value":"application/json"},{"name":"User-Agent","value":"insomnia/10.3.0"}],"authentication":{},"metaSortKey":-1738792698761,"isPrivate":false,"pathParameters":[],"settingStoreCookies":true,"settingSendCookies":true,"settingDisableRenderRequestBody":false,"settingEncodeUrl":true,"settingRebuildPath":true,"settingFollowRedirects":"global","_type":"request"},{"_id":"env_4b2c66ba61190bd51ed2d17aa0603d5b04a4a1a0","parentId":"wrk_fe311232e0ad4a948aa3f7055e7308cb","modified":1738792693908,"created":1738792693908,"name":"Base Environment","data":{},"dataPropertyOrder":null,"color":null,"isPrivate":false,"metaSortKey":1738792693909,"environmentType":"kv","_type":"environment"},{"_id":"jar_4b2c66ba61190bd51ed2d17aa0603d5b04a4a1a0","parentId":"wrk_fe311232e0ad4a948aa3f7055e7308cb","modified":1738792693909,"created":1738792693909,"name":"Default Jar","cookies":[],"_type":"cookie_jar"}]}